KEGG_parser/__init__.py
KEGG_parser/downloader.py
KEGG_parser/parsers.py
kegg_parser-0.0.14.dist-info/licenses/LICENSE
kegg_parser-0.0.14.dist-info/METADATA
kegg_parser-0.0.14.dist-info/WHEEL
kegg_parser-0.0.14.dist-info/top_level.txt
kegg_parser-0.0.14.dist-info/RECORD
