Metadata-Version: 2.4
Name: KEGG-parser
Version: 0.0.14
Summary: KEGG Parser: A tool for parsing and converting KEGG data into manipulable Python objects.
Author-email: Kumar Thurimella <lozuponelab.dev@olucdenver.onmicrosoft.com>
Requires-Python: >=3.8
License-File: LICENSE
Requires-Dist: aiohttp
Requires-Dist: asyncio
Requires-Dist: tqdm
Requires-Dist: requests
Dynamic: license-file
